[
  {
    "id": 1,
    "name": "Project",
    "scriptLetter": ["o"],
    "tags": ["az", "ti"],
    "description": "Cool project yesssssssssssss",
    "previewImage": "",
    "url": "",
    "projectImages": [],
    "expertise": [],
    "techUsed": [],
    "roleInProject": [],
    "bodyParagraphs": [
      {
        "title": "About",
        "body": "Maikati"
      }
    ]
  },
  {
    "id": 2,
    "name": "Project",
    "scriptLetter": ["o"],
    "tags": ["az", "ti"],
    "description": "Cool project yesssssssssssss",
    "previewImage": "",
    "url": "",
    "projectImages": [],
    "expertise": [],
    "techUsed": [],
    "roleInProject": [],
    "bodyParagraphs": [
      {
        "title": "About",
        "body": "Maikati"
      }
    ]
  },
  {
    "id": 3,
    "name": "Project",
    "scriptLetter": ["o"],
    "tags": ["az", "ti"],
    "description": "Cool project yesssssssssssss",
    "previewImage": "",
    "url": "",
    "projectImages": [],
    "expertise": [],
    "techUsed": [],
    "roleInProject": [],
    "bodyParagraphs": [
      {
        "title": "About",
        "body": "Maikati"
      }
    ]
  },
  {
    "id": 4,
    "name": "Project",
    "scriptLetter": ["o"],
    "tags": ["az", "ti"],
    "description": "Cool project yesssssssssssss",
    "previewImage": "",
    "url": "",
    "projectImages": [],
    "expertise": [],
    "techUsed": [],
    "roleInProject": [],
    "bodyParagraphs": [
      {
        "title": "About",
        "body": "Maikati"
      }
    ]
  }
]
